insta_browser/__init__.py
insta_browser/auth.py
insta_browser/browser.py
insta_browser/logger.py
insta_browser/version.py
insta_browser/db/__init__.py
insta_browser/db/browser_db.py
insta_browser/db/sql/init.sql
insta_browser/db/sql/migrations/1517145035.sql
insta_browser/processors/__init__.py
insta_browser/processors/base_processor.py
insta_browser/processors/feed_processor.py
insta_browser/processors/not_feed_processor.py
insta_browser-0.8.6.1.dist-info/METADATA
insta_browser-0.8.6.1.dist-info/RECORD
insta_browser-0.8.6.1.dist-info/WHEEL
insta_browser-0.8.6.1.dist-info/top_level.txt
