Metadata-Version: 2.1
Name: insta-browser
Version: 0.8.6.1
Summary: parsing/automation instagram.com
Home-page: https://github.com/kricha/insta_browser
Author: Aleksej Krichevsky
Author-email: krich.al.vl@gmail.com
License: MIT
Download-URL: https://github.com/kricha/insta_browser/archive/0.8.6.1.tar.gz
Keywords: parsing,bot,instabot,automation,likes
Platform: UNKNOWN
Classifier: Development Status :: 3 - Alpha
Classifier: License :: OSI Approved :: MIT License
Classifier: Natural Language :: English
Classifier: Programming Language :: Python
Classifier: Programming Language :: Python :: 3.6
Classifier: Topic :: Internet :: WWW/HTTP :: Browsers
Requires-Dist: selenium
Requires-Dist: tqdm
Requires-Dist: requests
